alamos/__init__.py
alamos/dev/__init__.py
alamos/environment.py
alamos/instrumentation.py
alamos/log.py
alamos/meta.py
alamos/noop.py
alamos/py.typed
alamos/trace.py
alamos-0.49.0.dist-info/METADATA
alamos-0.49.0.dist-info/WHEEL
alamos-0.49.0.dist-info/RECORD
