Metadata-Version: 2.4
Name: alamos
Version: 0.49.0
Summary: 
Author: Emiliano Bonilla
Author-email: ebonilla@synnaxlabs.com
Requires-Python: >=3.10,<4
Classifier: Programming Language :: Python :: 3
Classifier: Programming Language :: Python :: 3.10
Classifier: Programming Language :: Python :: 3.11
Classifier: Programming Language :: Python :: 3.12
Classifier: Programming Language :: Python :: 3.13
Classifier: Programming Language :: Python :: 3.14
Requires-Dist: opentelemetry-api (>=1.37.0,<2)
Requires-Dist: opentelemetry-sdk (>=1.37.0,<2)
Requires-Dist: pydantic (>=2.12.4,<3.0)
Requires-Dist: uptrace (>=1.37.0,<2)
